kython/__init__.py
kython/pl.py
kython/pp.py
kython-1.4.1.dist-info/LICENSE
kython-1.4.1.dist-info/METADATA
kython-1.4.1.dist-info/WHEEL
kython-1.4.1.dist-info/top_level.txt
kython-1.4.1.dist-info/RECORD
