Metadata-Version: 2.1
Name: kython
Version: 1.4.1
Summary: Python Library to compute and plot phylogeny Kmer signatures
Home-page: http://github.com/LeroyAdrien/Kython
Author: Adrien Leroy, Alex Lence, Simon Chardin
Author-email: leroy.adrien.76@gmail.com
License: MIT
Platform: UNKNOWN
Requires-Dist: PyQt5
Requires-Dist: biopython
Requires-Dist: ete3
Requires-Dist: matplotlib
Requires-Dist: ncbi-genome-download
Requires-Dist: numpy
Requires-Dist: pandas
Requires-Dist: scipy
